quicklogs/__init__.py
quicklogs/quicklogs.py
quicklogs-2.0.1.dist-info/METADATA
quicklogs-2.0.1.dist-info/WHEEL
quicklogs-2.0.1.dist-info/top_level.txt
quicklogs-2.0.1.dist-info/RECORD
