Metadata-Version: 2.4
Name: quicklogs
Version: 2.0.1
Summary: Easily configure Python loggers.
Author-email: Dan Kelleher <kelleherjdan@gmail.com>
License: MIT
Keywords: logs,logger,loggers,logging
Classifier: Programming Language :: Python
Classifier: Programming Language :: Python :: 3
Classifier: Topic :: Software Development
Classifier: Topic :: Software Development :: Libraries
Classifier: Topic :: Software Development :: Libraries :: Python Modules
Classifier: Topic :: System :: Logging
Provides-Extra: dev
Requires-Dist: black; extra == "dev"
Requires-Dist: pytest; extra == "dev"
